status_page/__init__.py
status_page/config.py
status_page/run.py
status_page/analytics/__init__.py
status_page/analytics/ping.py
status_page/analytics/version.py
status_page/analytics/web.py
status_page/models/User.py
status_page/models/__init__.py
status_page/routes/__init__.py
status_page/routes/routes.py
status_page/static/logo.png
status_page/static/style.css
status_page/templates/base.html
status_page/templates/display.html
status_page/templates/header.html
status_page/templates/init.html
status_page/templates/login.html
status_page/utils/__init__.py
status_page/utils/crypto.py
status_page/utils/env.py
status_page/utils/initialize.py
status_page-0.1.1.dist-info/LICENSE
status_page-0.1.1.dist-info/METADATA
status_page-0.1.1.dist-info/WHEEL
status_page-0.1.1.dist-info/top_level.txt
status_page-0.1.1.dist-info/RECORD
