Metadata-Version: 2.1
Name: status-page
Version: 0.1.1
Summary: A Server/Service Status Page
Home-page: https://gitlab.namibsun.net/namibsun/python/status-page
Author: Hermann Krumrey
Author-email: hermann@krumreyh.com
License: GNU GPL3
Platform: UNKNOWN
Classifier: License :: OSI Approved :: GNU General Public License v3 (GPLv3)
Requires-Dist: requests
Requires-Dist: bcrypt
Requires-Dist: werkzeug
Requires-Dist: flask-login
Requires-Dist: flask-sqlalchemy
Requires-Dist: sqlalchemy
Requires-Dist: flask
